argconf/__init__.py
argconf/argconf.py
argconf-0.3.4.dist-info/METADATA
argconf-0.3.4.dist-info/WHEEL
argconf-0.3.4.dist-info/top_level.txt
argconf-0.3.4.dist-info/RECORD
