Metadata-Version: 2.1
Name: argconf
Version: 0.3.4
Summary: Simple config and argument parsing with nested conf structure
Home-page: 
Author: Norman Müller
Author-email: norman.mueller@tum.de
Classifier: Programming Language :: Python :: 3
Classifier: License :: OSI Approved :: MIT License
Classifier: Operating System :: OS Independent
Requires-Python: >=3.6
Requires-Dist: pyhocon
Requires-Dist: python-box
Requires-Dist: omegaconf
